Metadata-Version: 1.1
Name: SQLAlchemy-Norm
Version: 0.0.5
Summary: Normalize SQLAlchemy Object to Plain dict and list
Home-page: https://github.com/haruair/sqlalchemy-norm
Author: Edward Kim
Author-email: onward.edkim@gmail.com
License: BSD
Platform: any
Classifier: Environment :: Web Environment
Classifier: Intended Audience :: Developers
Classifier: License :: OSI Approved :: BSD License
Classifier: Operating System :: OS Independent
Classifier: Programming Language :: Python
Classifier: Programming Language :: Python :: 2
Classifier: Programming Language :: Python :: 2.7
Classifier: Programming Language :: Python :: 3
Classifier: Programming Language :: Python :: 3.3
Classifier: Programming Language :: Python :: 3.4
Classifier: Programming Language :: Python :: 3.5
Classifier: Topic :: Internet :: WWW/HTTP :: Dynamic Content
Classifier: Topic :: Software Development :: Libraries :: Python Modules
